Rysan/__init__.py
Rysan-0.0.0.dist-info/METADATA
Rysan-0.0.0.dist-info/WHEEL
Rysan-0.0.0.dist-info/top_level.txt
Rysan-0.0.0.dist-info/RECORD
